protocolify
