Metadata-Version: 1.0
Name: django-protocolify
Version: 0.1.1
Summary: Template tag to change the protocol of URLs in links.
Home-page: https://github.com/bradleyayers/django-protocolify/
Author: Bradley Ayers
Author-email: bradley.ayers@gmail.com
License: UNKNOWN
Platform: UNKNOWN
Classifier: Environment :: Web Environment
Classifier: Framework :: Django
Classifier: Intended Audience :: Developers
Classifier: Operating System :: OS Independent
Classifier: Programming Language :: Python
Classifier: Topic :: Internet :: WWW/HTTP
Classifier: Topic :: Internet :: WWW/HTTP :: Dynamic Content
Classifier: Topic :: Software Development :: Libraries :: Python Modules
